{"_type":"export","__export_format":4,"__export_date":"2020-01-20T16:26:48.940Z","__export_source":"insomnia.desktop.app:v7.0.6","resources":[{"_id":"req_a7180e4c9929478d98125ff2637125db","authentication":{},"body":{"mimeType":"application/json","text":"{\t\"token\":\"eyJhbGciOiJIUzI1NiIsInR5cCI6IkpXVCJ9.eyJpZCI6MSwiaWF0IjoxNTc4NDIyODM1fQ.ixJoY9SL9C5b_0x8O97EPs-GJooAsu6Ixa_g57rQvSI\"\n}"},"created":1576868180661,"description":"","headers":[{"id":"pair_d3e8a35160f3475b9d91254a1fa60f1f","name":"Content-Type","value":"application/json"}],"isPrivate":false,"metaSortKey":-1576771896062,"method":"GET","modified":1578422854584,"name":"Verify Token","parameters":[],"parentId":"fld_988c95c382144ec6afc289428be98a62","settingDisableRenderRequestBody":false,"settingEncodeUrl":true,"settingFollowRedirects":"global","settingRebuildPath":true,"settingSendCookies":true,"settingStoreCookies":true,"url":"{{ base_url  }}/verify-token","_type":"request"},{"_id":"fld_988c95c382144ec6afc289428be98a62","created":1576868180647,"description":"","environment":{},"environmentPropertyOrder":null,"metaSortKey":-1576496401776,"modified":1576868180647,"name":"Login","parentId":"fld_fe933d988c9a426e9635cbbc823f47a6","_type":"request_group"},{"_id":"fld_fe933d988c9a426e9635cbbc823f47a6","created":1576868180496,"description":"","environment":{},"environmentPropertyOrder":null,"metaSortKey":-1573311216365.5,"modified":1576868180687,"name":"Ecommerce","parentId":"wrk_051d776c160f486dafd61251646c807b","_type":"request_group"},{"_id":"wrk_051d776c160f486dafd61251646c807b","created":1560434117482,"description":"","modified":1560434117482,"name":"Insomnia","parentId":null,"_type":"workspace"},{"_id":"req_40acc242988b4c0e9083d38bac2d861f","authentication":{},"body":{"mimeType":"application/json","text":"{\n\t\"email\":\"mesquini@live.com\",\n\t\"pass\":\"asd\"\n}"},"created":1576868180654,"description":"","headers":[{"id":"pair_26d375ad3c564e67b637151a3f873fd0","name":"Content-Type","value":"application/json"}],"isPrivate":false,"metaSortKey":-1576496413981,"method":"POST","modified":1576868180654,"name":"Login","parameters":[],"parentId":"fld_988c95c382144ec6afc289428be98a62","settingDisableRenderRequestBody":false,"settingEncodeUrl":true,"settingFollowRedirects":"global","settingRebuildPath":true,"settingSendCookies":true,"settingStoreCookies":true,"url":"{{ base_url  }}/login","_type":"request"},{"_id":"req_c8eb6c964e3649688d7e856233932a9f","authentication":{},"body":{},"created":1576868180596,"description":"","headers":[],"isPrivate":false,"metaSortKey":-1576089098605,"method":"GET","modified":1578581002725,"name":"findOne","parameters":[],"parentId":"fld_0a8e0d78a3094d0aa3b18f6b2a454bc4","settingDisableRenderRequestBody":false,"settingEncodeUrl":true,"settingFollowRedirects":"global","settingRebuildPath":true,"settingSendCookies":true,"settingStoreCookies":true,"url":"{{ base_url  }}/product/16","_type":"request"},{"_id":"fld_0a8e0d78a3094d0aa3b18f6b2a454bc4","created":1576868180571,"description":"","environment":{},"environmentPropertyOrder":null,"metaSortKey":-1576067060195,"modified":1576868180571,"name":"Product_photos","parentId":"fld_fe933d988c9a426e9635cbbc823f47a6","_type":"request_group"},{"_id":"req_cc2e6b0dc81740458c53c31aead6cb26","authentication":{},"body":{"mimeType":"multipart/form-data","params":[{"fileName":"C:\\Users\\victor.mesquini\\Downloads\\cc.jpg","id":"pair_591b52e2287543ee95731a823b61f63e","name":"file","type":"file","value":""}]},"created":1576868180587,"description":"","headers":[{"id":"pair_242879a4bac64fcb8233c3fccab25597","name":"Content-Type","value":"multipart/form-data"}],"isPrivate":false,"metaSortKey":-1576067069176,"method":"POST","modified":1578332315341,"name":"create","parameters":[],"parentId":"fld_0a8e0d78a3094d0aa3b18f6b2a454bc4","settingDisableRenderRequestBody":false,"settingEncodeUrl":true,"settingFollowRedirects":"global","settingRebuildPath":true,"settingSendCookies":true,"settingStoreCookies":true,"url":"{{ base_url  }}/new-product/4/photos","_type":"request"},{"_id":"req_9f1e89f420054680a9c7c768381db69a","authentication":{},"body":{"mimeType":"application/json","text":"{\n\t\"name\" : \"careira\"\n}"},"created":1576868180553,"description":"","headers":[{"id":"pair_3e9e024fa3544f1fb3484052f540c891","name":"Content-Type","value":"application/json"}],"isPrivate":false,"metaSortKey":-1576235892050,"method":"PUT","modified":1576868180553,"name":"Update","parameters":[],"parentId":"fld_5634362c2ad448cab4469284d08cd51d","settingDisableRenderRequestBody":false,"settingEncodeUrl":true,"settingFollowRedirects":"global","settingRebuildPath":true,"settingSendCookies":true,"settingStoreCookies":true,"url":"{{ base_url  }}/product/4","_type":"request"},{"_id":"fld_5634362c2ad448cab4469284d08cd51d","created":1576868180514,"description":"","environment":{},"environmentPropertyOrder":null,"metaSortKey":-1576063154093,"modified":1576868180514,"name":"Product","parentId":"fld_fe933d988c9a426e9635cbbc823f47a6","_type":"request_group"},{"_id":"req_b4dfc1afb9dd4a6e80631d58a7d857ee","authentication":{},"body":{},"created":1576868180544,"description":"","headers":[],"isPrivate":false,"metaSortKey":-1576233033830,"method":"DELETE","modified":1578580842792,"name":"Delete","parameters":[],"parentId":"fld_5634362c2ad448cab4469284d08cd51d","settingDisableRenderRequestBody":false,"settingEncodeUrl":true,"settingFollowRedirects":"global","settingRebuildPath":true,"settingSendCookies":true,"settingStoreCookies":true,"url":"{{ base_url  }}/product/14","_type":"request"},{"_id":"req_cf978ec31dbd45ec818765ccbd359205","authentication":{},"body":{},"created":1576868180536,"description":"","headers":[],"isPrivate":false,"metaSortKey":-1576063584300,"method":"GET","modified":1578655401255,"name":"findAll","parameters":[],"parentId":"fld_5634362c2ad448cab4469284d08cd51d","settingDisableRenderRequestBody":false,"settingEncodeUrl":true,"settingFollowRedirects":"global","settingRebuildPath":true,"settingSendCookies":true,"settingStoreCookies":true,"url":"{{ base_url  }}/products?paginate=2&page=3","_type":"request"},{"_id":"req_9281f8c31c354be4a60285b14f7c1a9d","authentication":{},"body":{},"created":1576868180561,"description":"","headers":[],"isPrivate":false,"metaSortKey":-1576063373671.5,"method":"GET","modified":1576868180561,"name":"findLike","parameters":[],"parentId":"fld_5634362c2ad448cab4469284d08cd51d","settingDisableRenderRequestBody":false,"settingEncodeUrl":true,"settingFollowRedirects":"global","settingRebuildPath":true,"settingSendCookies":true,"settingStoreCookies":true,"url":"{{ base_url  }}/product-search/co?paginate=3&page=1","_type":"request"},{"_id":"req_f834ccca6d094169990a0795923aeb73","authentication":{},"body":{"mimeType":"application/json","text":"{\n\t\"name\" : \"Ventilador\",\n\t\"quantity\" : 100,\n\t\"price\": 250.5\n}"},"created":1576868180526,"description":"","headers":[{"disabled":false,"id":"pair_054961cdf13144699ea0df9656670fb6","name":"Content-Type","value":"application/json"},{"description":"","id":"pair_7c79ecc794804bc292149efd90906059","name":"x-access-token","value":"eyJhbGciOiJIUzI1NiIsInR5cCI6IkpXVCJ9.eyJpZCI6MSwiaWF0IjoxNTc2NTE1ODMwfQ.qorTbKGW3n2S5cdv2ajoCilI3HkTN1zxmENTlyRfRQ0"},{"description":"","id":"pair_2983424875074b80a2236b6bcf31e3f0","name":"","value":""}],"isPrivate":false,"metaSortKey":-1576063163043,"method":"POST","modified":1576868180526,"name":"create","parameters":[],"parentId":"fld_5634362c2ad448cab4469284d08cd51d","settingDisableRenderRequestBody":false,"settingEncodeUrl":true,"settingFollowRedirects":"global","settingRebuildPath":true,"settingSendCookies":true,"settingStoreCookies":true,"url":"{{ base_url  }}/new-product","_type":"request"},{"_id":"req_e60892e022074bf780992dea950262e5","authentication":{},"body":{"mimeType":"application/json","text":"{\n\t\"isAdm\" : true\n}"},"created":1576868180639,"description":"","headers":[{"id":"pair_3e9e024fa3544f1fb3484052f540c891","name":"Content-Type","value":"application/json"}],"isPrivate":false,"metaSortKey":-1576235892050,"method":"PUT","modified":1576868180639,"name":"Update","parameters":[],"parentId":"fld_61d7d5128d584b6480bfb2c8339e5695","settingDisableRenderRequestBody":false,"settingEncodeUrl":true,"settingFollowRedirects":"global","settingRebuildPath":true,"settingSendCookies":true,"settingStoreCookies":true,"url":"{{ base_url  }}/user/1","_type":"request"},{"_id":"fld_61d7d5128d584b6480bfb2c8339e5695","created":1576868180604,"description":"","environment":{},"environmentPropertyOrder":null,"metaSortKey":-1576063150393,"modified":1576868180604,"name":"User","parentId":"fld_fe933d988c9a426e9635cbbc823f47a6","_type":"request_group"},{"_id":"req_b0127889d4594034a1a7c42bbd1c9614","authentication":{},"body":{},"created":1576868180629,"description":"","headers":[],"isPrivate":false,"metaSortKey":-1576233033830,"method":"DELETE","modified":1576868180629,"name":"Delete","parameters":[],"parentId":"fld_61d7d5128d584b6480bfb2c8339e5695","settingDisableRenderRequestBody":false,"settingEncodeUrl":true,"settingFollowRedirects":"global","settingRebuildPath":true,"settingSendCookies":true,"settingStoreCookies":true,"url":"{{ base_url  }}/product/3","_type":"request"},{"_id":"req_02df1dca7f5844c9a076c28659d6ca5f","authentication":{},"body":{},"created":1576868180621,"description":"","headers":[],"isPrivate":false,"metaSortKey":-1576063584300,"method":"GET","modified":1576868180621,"name":"findOne","parameters":[],"parentId":"fld_61d7d5128d584b6480bfb2c8339e5695","settingDisableRenderRequestBody":false,"settingEncodeUrl":true,"settingFollowRedirects":"global","settingRebuildPath":true,"settingSendCookies":true,"settingStoreCookies":true,"url":"{{ base_url  }}/user/2","_type":"request"},{"_id":"req_006e5c9ff1254834a8912925ac09b129","authentication":{},"body":{"mimeType":"application/json","text":"{\n\t\"name\" : \"victor\",\n\t\"pass\" : \"asd\",\n\t\"email\" : \"mesquini@live.com\",\n\t\"adm\": true\n}"},"created":1576868180612,"description":"","headers":[{"id":"pair_054961cdf13144699ea0df9656670fb6","name":"Content-Type","value":"application/json"}],"isPrivate":false,"metaSortKey":-1576063163043,"method":"POST","modified":1576868180612,"name":"create","parameters":[],"parentId":"fld_61d7d5128d584b6480bfb2c8339e5695","settingDisableRenderRequestBody":false,"settingEncodeUrl":true,"settingFollowRedirects":"global","settingRebuildPath":true,"settingSendCookies":true,"settingStoreCookies":true,"url":"{{ base_url  }}/new-user","_type":"request"},{"_id":"env_85c0ebdaaa6c9e86a39b0232df75dce58fb94544","color":null,"created":1560434117534,"data":{"base_url":"http://localhost:3333"},"dataPropertyOrder":{"&":["base_url"]},"isPrivate":false,"metaSortKey":1560434117534,"modified":1570480517840,"name":"Base Environment","parentId":"wrk_051d776c160f486dafd61251646c807b","_type":"environment"},{"_id":"jar_85c0ebdaaa6c9e86a39b0232df75dce58fb94544","cookies":[{"creation":"2019-08-13T13:45:49.332Z","domain":"app.valuegaia.com.br","hostOnly":true,"id":"4015151173120908","key":"AWSELB","lastAccessed":"2020-01-17T10:54:22.054Z","path":"/","value":"A37F471B0A6F77E187FC045FBF17AC47A2D775F57160A6F2F1F0DFC72C6457160373A51C25B2A6839548F833DCC233DB74D46A646C670D2D9EF25FD67B0D2BBFF6B7F40619"}],"created":1560434117543,"modified":1579258462094,"name":"Default Jar","parentId":"wrk_051d776c160f486dafd61251646c807b","_type":"cookie_jar"}]}